envoy/ci/report/__init__.py
envoy/ci/report/ci.py
envoy/ci/report/cmd.py
envoy/ci/report/exceptions.py
envoy/ci/report/interface.py
envoy/ci/report/py.typed
envoy/ci/report/runner.py
envoy/ci/report/typing.py
envoy/ci/report/abstract/__init__.py
envoy/ci/report/abstract/filters.py
envoy/ci/report/abstract/format.py
envoy/ci/report/abstract/runner.py
envoy/ci/report/abstract/runs.py
envoy.ci.report-0.0.3.dist-info/METADATA
envoy.ci.report-0.0.3.dist-info/WHEEL
envoy.ci.report-0.0.3.dist-info/entry_points.txt
envoy.ci.report-0.0.3.dist-info/namespace_packages.txt
envoy.ci.report-0.0.3.dist-info/top_level.txt
envoy.ci.report-0.0.3.dist-info/RECORD
